uniswapSim/__init__.py
uniswapSim/uniswapsim.py
uniswapsim-0.0.1.dist-info/METADATA
uniswapsim-0.0.1.dist-info/WHEEL
uniswapsim-0.0.1.dist-info/licenses/LICENSE
uniswapsim-0.0.1.dist-info/RECORD
