Metadata-Version: 2.1
Name: uniswapSim
Version: 0.0.1
Summary: An implementation of the Uniswap protocol in Python
Project-URL: Homepage, https://github.com/pypa/sampleproject
Project-URL: Bug Tracker, https://github.com/pypa/sampleproject/issues
Author-email: Khaled Grira <kh.grira@gmail.com>
License-File: LICENSE
Classifier: License :: OSI Approved :: MIT License
Classifier: Operating System :: OS Independent
Classifier: Programming Language :: Python :: 3
Requires-Python: >=3.7
